MANIFEST.in
README.md
setup.cfg
setup.py
requirements/requirements.txt
scrapy_selenium_mark/__init__.py
scrapy_selenium_mark/http.py
scrapy_selenium_mark/middlewares.py
scrapy_selenium_mark.egg-info/PKG-INFO
scrapy_selenium_mark.egg-info/SOURCES.txt
scrapy_selenium_mark.egg-info/dependency_links.txt
scrapy_selenium_mark.egg-info/requires.txt
scrapy_selenium_mark.egg-info/top_level.txt
tests/__init__.py
tests/test_cases.py
tests/test_middlewares.py