Metadata-Version: 1.0
Name: scrapy-selenium-mark
Version: 0.0.10
Summary: Scrapy with selenium
Home-page: https://github.com/markronquillo/scrapy-selenium
Author: UNKNOWN
Author-email: UNKNOWN
License: UNKNOWN
Platform: UNKNOWN
